minestrone/__init__.py
minestrone/element/__init__.py
minestrone/formatter.py
minestrone_soup-0.1.1.dist-info/WHEEL
minestrone_soup-0.1.1.dist-info/METADATA
minestrone_soup-0.1.1.dist-info/RECORD
